Workbook

Sheet Books
A1: Corner Books — full catalogue
A2: Shop markup (×wholesale) | C2: 1.45 | D2: Source: autoPrice() in index.html — round(cost × 1.45) − $0.10
A4: # | B4: Title | C4: Author | D4: Year | E4: Genre | F4: Moods | G4: Pace | H4: Weight | I4: Themes | J4: Wholesale cost ($) | K4: Shop price ($) | L4: Avg reader rating | M4: No. of ratings | N4: Blurb
A5: 1 | B5: Never Let Me Go | C5: Kazuo Ishiguro | D5: 2005 | E5: Literary | F5: melancholy, contemplative | G5: slow | H5: medium | I5: memory, mortality, friendship | J5: 29 | K5: =ROUND(J5*$C$2,0)-0.1 -> 41.9 | L5: 3.99 | M5: 950000 | N5: Three friends raised at Hailsham, a secluded English boarding school, spend their childhood painting, gossiping and slowly noticing that the adults around them will never quite look them in the eye. As they grow into a wider, ordinary-seeming England, the truth of what they were made for closes in with a quiet, unhurried dread. Ishiguro never raises his voice; the horror is entirely in the calm.
A6: 2 | B6: The Remains of the Day | C6: Kazuo Ishiguro | D6: 1989 | E6: Literary | F6: melancholy, contemplative | G6: slow | H6: medium | I6: regret, duty, class | J6: 28 | K6: =ROUND(J6*$C$2,0)-0.1 -> 40.9 | L6: 4.09 | M6: 350000 | N6: Stevens, an ageing English butler, sets out on a motoring holiday across the West Country and finds himself reliving thirty years of service at Darlington Hall — the diplomatic dinners, the housekeeper he never allowed himself to love, the great house's slow slide toward a war his employer misjudged. Every sentence is precisely, devastatingly polite. What he cannot say out loud is the whole book.
A7: 3 | B7: Klara and the Sun | C7: Kazuo Ishiguro | D7: 2021 | E7: Literary | F7: melancholy, hopeful | G7: slow | H7: medium | I7: love, loneliness, faith | J7: 32 | K7: =ROUND(J7*$C$2,0)-0.1 -> 45.9 | L7: 3.98 | M7: 320000 | N7: Klara is an Artificial Friend, built to be chosen and to love whichever child chooses her, and she watches the street outside her shop window with a solar-powered faith that borders on religion. When a frail girl named Josie finally takes her home, Klara's devotion is put to uses far stranger and sadder than companionship. A story about love asked to do an impossible job.
A8: 4 | B8: Beloved | C8: Toni Morrison | D8: 1987 | E8: Literary | F8: unsettling, melancholy | G8: slow | H8: heavy | I8: memory, slavery, motherhood | J8: 31 | K8: =ROUND(J8*$C$2,0)-0.1 -> 44.9 | L8: 3.87 | M8: 420000 | N8: Sethe escaped slavery in Kentucky and built a life in postwar Ohio, but the house at 124 Bluestone Road is haunted — first by a restless presence, then by a strange young woman who arrives at the door calling herself Beloved. Morrison writes the unspeakable act at the center of the novel with a force that rearranges everything around it. A landmark of American fiction.
A9: 5 | B9: Norwegian Wood | C9: Haruki Murakami | D9: 1987 | E9: Literary | F9: melancholy, contemplative | G9: steady | H9: medium | I9: grief, first love, youth | J9: 30 | K9: =ROUND(J9*$C$2,0)-0.1 -> 43.9 | L9: 4.04 | M9: 520000 | N9: A song on an airplane sends Toru Watanabe back to 1960s Tokyo, to a fragile, grieving girl named Naoko who carries the death of the boy they both loved, and to the vivid, unapologetic Midori who wants him to choose life instead of memory. Quiet, sensual and steeped in loss, it is the Murakami novel without a single talking cat.
A10: 6 | B10: Kafka on the Shore | C10: Haruki Murakami | D10: 2002 | E10: Literary | F10: unsettling, contemplative | G10: steady | H10: medium | I10: fate, identity, dreams | J10: 33 | K10: =ROUND(J10*$C$2,0)-0.1 -> 47.9 | L10: 4.11 | M10: 480000 | N10: A fifteen-year-old runs away from an Oedipal prophecy under the alias Kafka Tamura, while across town an old man who lost his memory in a wartime incident discovers he can talk to cats. Their stories run in parallel and then, impossibly, touch. Fish fall from the sky, a forest swallows soldiers whole, and Murakami insists the dream logic is the point.
A11: 7 | B11: One Hundred Years of Solitude | C11: Gabriel Garcia Marquez | D11: 1967 | E11: Literary | F11: contemplative, melancholy | G11: slow | H11: heavy | I11: family, time, solitude | J11: 34 | K11: =ROUND(J11*$C$2,0)-0.1 -> 48.9 | L11: 4.11 | M11: 850000 | N11: Jose Arcadio Buendia founds the town of Macondo on a whim, and seven generations of his descendants proceed to fall in love, wage war, chase gold and gypsy science, and repeat their ancestors' names and mistakes until the whole line is written into a manuscript that has been prophesying them all along. The founding text of magical realism, and still the best argument for it.
A12: 8 | B12: The God of Small Things | C12: Arundhati Roy | D12: 1997 | E12: Literary | F12: melancholy, unsettling | G12: slow | H12: heavy | I12: family, caste, childhood | J12: 30 | K12: =ROUND(J12*$C$2,0)-0.1 -> 43.9 | L12: 3.9 | M12: 210000 | N12: Twins Estha and Rahel grow up in a pickle factory in Kerala, watched over by a family that observes every caste and class rule except the one that matters most. One afternoon at the river breaks the family permanently, and Roy circles that afternoon for the length of the novel, closing in a little more with every pass. Won the Booker Prize; still stings on a second reading.
A13: 9 | B13: Things Fall Apart | C13: Chinua Achebe | D13: 1958 | E13: Literary | F13: melancholy, contemplative | G13: steady | H13: medium | I13: tradition, change, masculinity | J13: 26 | K13: =ROUND(J13*$C$2,0)-0.1 -> 37.9 | L13: 3.76 | M13: 280000 | N13: Okonkwo is a respected wrestler, farmer and warrior in his Igbo village, a man who has built his whole identity on not being his weak, gentle father. When British missionaries and colonial administrators arrive, the world that made Okonkwo's strength meaningful starts to dissolve around him. The first great African novel written in English, and still the clearest account of what colonialism actually costs.
A14: 10 | B14: Pachinko | C14: Min Jin Lee | D14: 2017 | E14: Literary | F14: melancholy, hopeful | G14: steady | H14: heavy | I14: family, migration, belonging | J14: 35 | K14: =ROUND(J14*$C$2,0)-0.1 -> 50.9 | L14: 4.32 | M14: 650000 | N14: Sunja, a poor fisherman's daughter in Japanese-occupied Korea, makes one impulsive choice as a teenager that sends her family into exile in Japan for four generations. Lee follows them through war, poverty, the shame economy of Korean-run pachinko parlors and the quiet cruelty of never quite belonging, in prose so unshowy you forget how much ground it's covering.
A15: 11 | B15: Gone Girl | C15: Gillian Flynn | D15: 2012 | E15: Crime | F15: thrilling, unsettling | G15: fast | H15: medium | I15: marriage, deceit, media | J15: 29 | K15: =ROUND(J15*$C$2,0)-0.1 -> 41.9 | L15: 4.11 | M15: 2800000 | N15: On the morning of their fifth wedding anniversary, Amy Dunne vanishes from the home she shares with her husband Nick, and the evidence — plus his own strange, guarded behaviour on television — starts turning the whole country against him. Flynn alternates his account with Amy's diary in a structure built entirely around a mid-book reversal that changes what every earlier page meant.
A16: 12 | B16: The Girl with the Dragon Tattoo | C16: Stieg Larsson | D16: 2005 | E16: Crime | F16: thrilling, unsettling | G16: fast | H16: heavy | I16: corruption, revenge, secrets | J16: 30 | K16: =ROUND(J16*$C$2,0)-0.1 -> 43.9 | L16: 4.14 | M16: 3200000 | N16: Disgraced financial journalist Mikael Blomkvist is hired by an aging industrialist to solve his niece's disappearance forty years earlier, and finds his sharpest ally in Lisbeth Salander, a bisexual hacker with a photographic memory and a well-earned distrust of every institution in Sweden. What starts as a cold-case mystery opens into corporate fraud, Nazi sympathizers and a family that has been hiding something monstrous for decades.
... A38: 34 | B38: Zero to One | C38: Peter Thiel | D38: 2014 | E38: Business | F38: contemplative | G38: fast | H38: light | I38: startups, monopoly, contrarian | J38: 29 | K38: =ROUND(J38*$C$2,0)-0.1 -> 41.9 | L38: 4.18 | M38: 260000 | N38: PayPal co-founder Peter Thiel argues that real progress isn't copying what already works — going from 1 to n — but building something genuinely new that didn't exist before, going from 0 to 1, and that the companies which matter most are the ones brave enough to aim for a temporary monopoly rather than compete in a crowded market. Contrarian, opinionated, and built from his own Silicon Valley notebook.
A39: 35 | B39: Meditations | C39: Marcus Aurelius | D39: c. AD 180 | E39: Philosophy | F39: contemplative, comforting | G39: slow | H39: medium | I39: stoicism, duty, death | J39: 21 | K39: =ROUND(J39*$C$2,0)-0.1 -> 29.9 | L39: 4.19 | M39: 350000 | N39: Written as private notes to himself during military campaigns, never intended for publication, this is the Roman emperor Marcus Aurelius working through Stoic philosophy in real time — reminding himself to control his temper, accept what he cannot change, treat others with patience, and prepare, without self-pity, for his own death. Nearly two thousand years later it still reads like advice meant for you specifically.
A40: 36 | B40: The Myth of Sisyphus | C40: Albert Camus | D40: 1942 | E40: Philosophy | F40: contemplative, melancholy | G40: slow | H40: heavy | I40: absurdity, meaning, suicide | J40: 24 | K40: =ROUND(J40*$C$2,0)-0.1 -> 34.9 | L40: 4.05 | M40: 90000 | N40: Camus opens with the claim that the only truly serious philosophical question is whether life is worth living, then spends the essay building his answer around the Greek myth of Sisyphus, condemned to push a boulder up a hill forever, only for it to roll back down every time. His conclusion — that we must imagine Sisyphus happy — is one of the most quoted, and most argued-over, lines in modern philosophy.
A41: 37 | B41: Devotions | C41: Mary Oliver | D41: 2017 | E41: Poetry | F41: comforting, contemplative | G41: slow | H41: light | I41: nature, attention, grace | J41: 35 | K41: =ROUND(J41*$C$2,0)-0.1 -> 50.9 | L41: 4.46 | M41: 40000 | N41: This career-spanning selection gathers roughly fifty years of Mary Oliver's poems — about geese crossing a clear sky, ponds at dawn, the discipline of simply paying attention to the natural world — chosen by Oliver herself as her definitive collection shortly before her death. Plainspoken, unsentimental and quietly devotional, in the way its title promises.
A42: 38 | B42: Milk and Honey | C42: Rupi Kaur | D42: 2014 | E42: Poetry | F42: melancholy, hopeful | G42: fast | H42: light | I42: healing, love, womanhood | J42: 26 | K42: =ROUND(J42*$C$2,0)-0.1 -> 37.9 | L42: 3.95 | M42: 800000 | N42: Structured in four movements — the hurting, the loving, the breaking, the healing — Rupi Kaur's debut collection pairs short, stripped-down free verse with her own minimalist line drawings to trace one relationship's collapse and the slow rebuilding of a self afterward. It became a publishing phenomenon and, for better or worse, defined an entire generation's idea of what a poem could look like on Instagram.
A43: 39 | B43: Where the Wild Things Are | C43: Maurice Sendak | D43: 1963 | E43: Children | F43: comforting, funny | G43: fast | H43: light | I43: temper, imagination, home | J43: 20 | K43: =ROUND(J43*$C$2,0)-0.1 -> 28.9 | L43: 4.23 | M43: 620000 | N43: Sent to bed without supper for wearing his wolf suit and making mischief, Max sails in his imagination to an island of enormous, snarling monsters — who promptly crown him their king because he's the wildest thing of all. He rules over a magnificent wild rumpus, then gets homesick and sails back to find his supper still warm. Ten sentences that changed picture books forever.
A44: 40 | B44: Charlotte's Web | C44: E.B. White | D44: 1952 | E44: Children | F44: comforting, melancholy | G44: fast | H44: light | I44: friendship, death, farm | J44: 19 | K44: =ROUND(J44*$C$2,0)-0.1 -> 27.9 | L44: 4.24 | M44: 1000000 | N44: Wilbur the pig is destined for the dinner table until Charlotte, a barn spider with an unusually good vocabulary, decides to save him by weaving flattering words about him into her web overnight. It works — but Charlotte's own life is running out on a much shorter clock than Wilbur's, and White never once softens that fact to spare young readers. Widely considered the best-selling children's paperback of all time.
A45: 41 | B45: Matilda | C45: Roald Dahl | D45: 1988 | E45: Children | F45: funny, hopeful | G45: fast | H45: light | I45: books, injustice, cleverness | J45: 21 | K45: =ROUND(J45*$C$2,0)-0.1 -> 29.9 | L45: 4.29 | M45: 1100000 | N45: Matilda Wormwood is a five-year-old genius stuck with parents who think television is more important than books and a headmistress who throws children by the pigtails, so she teaches herself to read, discovers the library, and — eventually — discovers she can move things with her mind. Dahl's last major children's novel and one of his most purely satisfying acts of revenge-on-behalf-of-kids.
A46: 42 | B46: The Little Prince | C46: Antoine de Saint-Exupery | D46: 1943 | E46: Children | F46: comforting, melancholy | G46: fast | H46: light | I46: innocence, love, loss | J46: 22 | K46: =ROUND(J46*$C$2,0)-0.1 -> 31.9 | L46: 4.32 | M46: 2100000 | N46: A pilot stranded in the Sahara after an engine failure meets a solemn little boy who has fallen to Earth from a tiny asteroid, and who asks unanswerable questions about sheep, roses and the strange priorities of grown-ups. Written by a working aviator not long before he disappeared on a wartime reconnaissance flight, it is a children's book that gets sadder, not simpler, the older you are when you read it.
A47: 43 | B47: Jane Eyre | C47: Charlotte Brontë | D47: 1847 | E47: Romance | F47: melancholy, hopeful | G47: steady | H47: medium | I47: independence, love, conscience | J47: 24 | K47: =ROUND(J47*$C$2,0)-0.1 -> 34.9 | L47: 4.15 | M47: 2100000 | N47: Orphaned, unloved and sent to the grim charity school at Lowood, Jane Eyre grows up plain, poor and absolutely unwilling to be anyone's lesser. As governess at Thornfield Hall she falls for its brooding master, Mr Rochester, but something in the house — a laugh in the night, a locked upper floor — keeps getting between them and happiness. A love story whose heroine insists, at great cost, on keeping her own soul.
A48: 44 | B48: Wuthering Heights | C48: Emily Brontë | D48: 1847 | E48: Romance | F48: unsettling, melancholy | G48: steady | H48: medium | I48: obsession, revenge, class | J48: 23 | K48: =ROUND(J48*$C$2,0)-0.1 -> 32.9 | L48: 3.88 | M48: 1600000 | N48: On the wind-scoured Yorkshire moors, the foundling Heathcliff and Catherine Earnshaw grow up wild together and become something fiercer than lovers. When she marries for position instead, he disappears, returns rich, and sets about destroying both their families across a generation. Less a romance than a storm: nobody behaves well, and that is the point.
A49: 45 | B49: Great Expectations | C49: Charles Dickens | D49: 1861 | E49: Literary | F49: contemplative, funny | G49: steady | H49: medium | I49: ambition, class, guilt | J49: 24 | K49: =ROUND(J49*$C$2,0)-0.1 -> 34.9 | L49: 3.79 | M49: 800000 | N49: Pip, a blacksmith's boy on the Kent marshes, is frightened half to death by an escaped convict, summoned to play at the decaying house of the jilted Miss Havisham, and then told that a secret benefactor will make him a gentleman in London. Dickens follows his rise with comedy and a slow-building ache, as Pip learns what his snobbery has cost the people who loved him first. A coming-of-age novel about money, shame and gratitude.
A50: 46 | B50: A Tale of Two Cities | C50: Charles Dickens | D50: 1859 | E50: History | F50: thrilling, melancholy | G50: steady | H50: medium | I50: revolution, sacrifice, resurrection | J50: 24 | K50: =ROUND(J50*$C$2,0)-0.1 -> 34.9 | L50: 3.86 | M50: 950000 | N50: London and Paris, from 1775 to the Terror. A doctor freed after eighteen years in the Bastille, his devoted daughter, a French aristocrat who has renounced his name and a dissolute English lawyer who happens to look exactly like him are all drawn toward the guillotine as the Revolution turns on itself. Dickens at his most theatrical, with one of the most famous openings — and closings — in English.
A51: 47 | B51: Moby-Dick | C51: Herman Melville | D51: 1851 | E51: Literary | F51: contemplative, thrilling | G51: slow | H51: heavy | I51: obsession, nature, fate | J51: 28 | K51: =ROUND(J51*$C$2,0)-0.1 -> 40.9 | L51: 3.53 | M51: 600000 | N51: Call him Ishmael. A restless young man signs onto the Nantucket whaler Pequod and discovers that its captain, Ahab, has a single purpose for the voyage: to hunt down the white whale that took his leg. Melville crams whaling lore, sermons, comedy, philosophy and stage drama around the chase, and the result is strange, sprawling and thunderous. Patience is rewarded with some of the most electric prose in English.
... A78: 74 | B78: Fahrenheit 451 | C78: Ray Bradbury | D78: 1953 | E78: Sci-Fi | F78: unsettling, hopeful | G78: fast | H78: light | I78: censorship, knowledge, conformity | J78: 21 | K78: =ROUND(J78*$C$2,0)-0.1 -> 29.9 | L78: 3.97 | M78: 2600000 | N78: Guy Montag is a fireman, which in his future America means he burns books, and the houses that hide them. Everyone around him is happily plugged into wall-sized televisions — until a strange teenage neighbour asks whether he is happy, and he steals a book. Bradbury's short, urgent novel about censorship, distraction and the people who memorise what is about to be lost.
A79: 75 | B79: The Odyssey | C79: Homer | D79: c. 8th century BC | E79: Poetry | F79: thrilling, hopeful | G79: steady | H79: medium | I79: homecoming, cunning, loyalty | J79: 25 | K79: =ROUND(J79*$C$2,0)-0.1 -> 35.9 | L79: 3.79 | M79: 1100000 | N79: Ten years after the fall of Troy, Odysseus still has not come home. He has outwitted a Cyclops, sailed past the Sirens and been held for years by a nymph, while back in Ithaca his wife Penelope stalls a hall full of suitors and his son Telemachus sets out to find him. The oldest adventure story in Western literature, and the model for every hero's journey since.
A80: 76 | B80: Gone with the Wind | C80: Margaret Mitchell | D80: 1936 | E80: History | F80: thrilling, melancholy | G80: steady | H80: heavy | I80: survival, love, loss | J80: 35 | K80: =ROUND(J80*$C$2,0)-0.1 -> 50.9 | L80: 4.31 | M80: 1300000 | N80: Scarlett O'Hara, the spoilt and spirited daughter of a Georgia plantation owner, loves a man she cannot have and marries men she does not love, as the American Civil War burns her world down. Surviving the siege of Atlanta and the hunger that follows, she becomes ruthless, and the roguish Rhett Butler is the only one who sees her clearly. A huge, gripping romance, though its nostalgia for the slave-owning South is hard for many readers to stomach today.
A81: 77 | B81: Rebecca | C81: Daphne du Maurier | D81: 1938 | E81: Horror | F81: unsettling, thrilling | G81: steady | H81: medium | I81: jealousy, identity, secrets | J81: 25 | K81: =ROUND(J81*$C$2,0)-0.1 -> 35.9 | L81: 4.25 | M81: 900000 | N81: A shy young woman working as a paid companion in Monte Carlo marries the wealthy widower Maxim de Winter and goes home with him to Manderley, his great house on the Cornish coast. Everything there still belongs to his first wife, Rebecca — her monogram, her rooms, her devoted housekeeper Mrs Danvers. 'Last night I dreamt I went to Manderley again': a psychological Gothic that tightens like a noose.
A82: 78 | B82: The Lord of the Rings | C82: J. R. R. Tolkien | D82: 1954 | E82: Fantasy | F82: thrilling, hopeful | G82: steady | H82: heavy | I82: courage, friendship, temptation | J82: 39 | K82: =ROUND(J82*$C$2,0)-0.1 -> 56.9 | L82: 4.53 | M82: 700000 | N82: Frodo Baggins inherits a plain gold ring from his uncle Bilbo and learns that it is the One Ring of the Dark Lord Sauron, who is searching for it. With a fellowship of hobbits, men, an elf, a dwarf and the wizard Gandalf, Frodo sets out to destroy it in the fire where it was forged. The founding text of modern fantasy, full of songs, languages and history, and a story of very small people doing very large things.
A83: 79 | B83: Catch-22 | C83: Joseph Heller | D83: 1961 | E83: Literary | F83: funny, unsettling | G83: steady | H83: heavy | I83: war, absurdity, bureaucracy | J83: 27 | K83: =ROUND(J83*$C$2,0)-0.1 -> 38.9 | L83: 3.99 | M83: 850000 | N83: On a small Mediterranean island in the Second World War, the bombardier Yossarian is convinced that everyone is trying to kill him — the enemy, and his own colonels, who keep raising the number of missions needed to go home. He tries to be declared insane, but anyone who asks to be excused from combat must be sane. That's the catch. A furious, circular black comedy about bureaucracy and war.
A84: 80 | B84: Slaughterhouse-Five | C84: Kurt Vonnegut | D84: 1969 | E84: Literary | F84: funny, melancholy | G84: fast | H84: light | I84: war, trauma, free will | J84: 24 | K84: =ROUND(J84*$C$2,0)-0.1 -> 34.9 | L84: 4.1 | M84: 1400000 | N84: Billy Pilgrim has come unstuck in time. He drifts between his childhood, his life as an optometrist in Ilium, New York, his abduction by aliens from Tralfamadore and the firebombing of Dresden, which he survived as a prisoner of war in an underground meat locker — as Vonnegut himself did. So it goes. A short, wry, heartbroken anti-war novel that refuses to tell its story in order.
A85: 81 | B85: The Stranger | C85: Albert Camus | D85: 1942 | E85: Literary | F85: contemplative, unsettling | G85: fast | H85: light | I85: absurdity, alienation, judgement | J85: 20 | K85: =ROUND(J85*$C$2,0)-0.1 -> 28.9 | L85: 4.02 | M85: 1100000 | N85: 'Mother died today. Or maybe yesterday; I can't be sure.' Meursault, a clerk in French Algiers, attends his mother's funeral without weeping, starts an affair, and weeks later shoots a man on a blazing beach for no reason he can name. His trial turns out to be less about the killing than about his refusal to feel what society expects. Camus' short, cool novel of the absurd.
A86: 82 | B86: The Metamorphosis | C86: Franz Kafka | D86: 1915 | E86: Literary | F86: unsettling, funny | G86: fast | H86: light | I86: alienation, family, duty | J86: 19 | K86: =ROUND(J86*$C$2,0)-0.1 -> 27.9 | L86: 3.84 | M86: 900000 | N86: Gregor Samsa, a travelling salesman who supports his whole family, wakes one morning to find he has been transformed into a monstrous insect. His first worry is that he will be late for work. Kafka's novella follows his family's reaction — horror, then resentment, then something worse — and is by turns absurd, darkly comic and deeply sad.
A87: 83 | B87: Invisible Man | C87: Ralph Ellison | D87: 1952 | E87: Literary | F87: contemplative, unsettling | G87: steady | H87: heavy | I87: identity, race, visibility | J87: 28 | K87: =ROUND(J87*$C$2,0)-0.1 -> 40.9 | L87: 3.89 | M87: 200000 | N87: From an underground room lit by 1,369 stolen light bulbs, an unnamed Black narrator tells how he went from a Southern college to Harlem, joining and leaving one movement after another, only to find that no one ever really sees him. Surreal, angry and as rhythmic as jazz, Ellison's novel won the National Book Award in 1953.
A88: 84 | B88: The Old Man and the Sea | C88: Ernest Hemingway | D88: 1952 | E88: Literary | F88: contemplative, hopeful | G88: fast | H88: light | I88: endurance, pride, nature | J88: 19 | K88: =ROUND(J88*$C$2,0)-0.1 -> 27.9 | L88: 3.79 | M88: 1100000 | N88: Santiago, an old Cuban fisherman, has gone eighty-four days without a catch. He rows far out into the Gulf Stream alone and hooks a giant marlin that tows his skiff for days. Hemingway's spare, luminous novella of endurance won him the Pulitzer Prize and helped win him the Nobel.
A89: 85 | B89: The Hound of the Baskervilles | C89: Arthur Conan Doyle | D89: 1902 | E89: Crime | F89: thrilling, unsettling | G89: fast | H89: light | I89: deduction, superstition, inheritance | J89: 21 | K89: =ROUND(J89*$C$2,0)-0.1 -> 29.9 | L89: 4.13 | M89: 450000 | N89: Sir Charles Baskerville is found dead at the edge of Dartmoor with a look of terror on his face, and near the body are the footprints of a gigantic hound. The family legend calls it a curse. Sherlock Holmes sends Dr Watson to guard the heir at a fog-bound manor among bogs, an escaped convict and suspicious neighbours. The best Holmes story, and the most atmospheric.
A90: 86 | B90: Their Eyes Were Watching God | C90: Zora Neale Hurston | D90: 1937 | E90: Literary | F90: hopeful, melancholy | G90: steady | H90: medium | I90: independence, love, voice | J90: 24 | K90: =ROUND(J90*$C$2,0)-0.1 -> 34.9 | L90: 3.94 | M90: 380000 | N90: Janie Crawford tells her friend Pheoby the story of her life: the marriage her grandmother arranged for her, a second husband who becomes mayor of an all-Black Florida town and silences her, and at last Tea Cake, a younger, laughing man who takes her down to the Everglades to work the muck. Hurston's rich Southern vernacular sings. A love story, and a story of a woman finding her own voice.
A91: 87 | B91: The Handmaid's Tale | C91: Margaret Atwood | D91: 1985 | E91: Sci-Fi | F91: unsettling, melancholy | G91: steady | H91: medium | I91: control, gender, resistance | J91: 27 | K91: =ROUND(J91*$C$2,0)-0.1 -> 38.9 | L91: 4.14 | M91: 2600000 | N91: In the Republic of Gilead, a theocracy that has overthrown the United States, fertile women are assigned to the households of powerful men to bear their children. Offred remembers her daughter, her husband, her job, her own name — all taken from her. Atwood said she put nothing in it that had not already happened somewhere in history, which is exactly what makes it frightening.
... A108: 104 | B108: Where the Crawdads Sing | C108: Delia Owens | D108: 2018 | E108: Literary | F108: melancholy, hopeful | G108: steady | H108: medium | I108: loneliness, nature, prejudice | J108: 30 | K108: =ROUND(J108*$C$2,0)-0.1 -> 43.9 | L108: 4.45 | M108: 3500000 | N108: Abandoned by her family one by one, Kya Clark grows up alone in a shack in the North Carolina marshes, the 'Marsh Girl' of the townsfolk of Barkley Cove, learning everything she knows from the gulls, the tides and the shells. When the town's golden boy is found dead in 1969, suspicion falls on her. Part coming-of-age story, part courtroom mystery, part love letter to the wild.
A109: 105 | B109: The Art of War | C109: Sun Tzu | D109: c. 5th century BC | E109: Business | F109: contemplative | G109: steady | H109: light | I109: strategy, leadership, conflict | J109: 19 | K109: =ROUND(J109*$C$2,0)-0.1 -> 27.9 | L109: 3.97 | M109: 300000 | N109: Thirteen short chapters on strategy attributed to the ancient Chinese general Sun Tzu: know your enemy and know yourself, win without fighting, attack where they are unprepared. Written for warring states, it has since been taken up by generals, CEOs, coaches and anyone who negotiates for a living. Quick to read, slow to finish thinking about.
A110: 106 | B110: The Prince | C110: Niccolò Machiavelli | D110: 1532 | E110: Philosophy | F110: contemplative, unsettling | G110: fast | H110: light | I110: power, politics, pragmatism | J110: 19 | K110: =ROUND(J110*$C$2,0)-0.1 -> 27.9 | L110: 3.84 | M110: 330000 | N110: Written by a Florentine diplomat out of a job, The Prince is a short handbook on how to win power and keep it: whether it is better to be loved or feared, when a ruler must break his word, why fortune favours the bold. Machiavelli's cool realism scandalised Europe and gave us the word 'Machiavellian'. Still read by politicians, executives and anyone who wonders how power really works.
A111: 107 | B111: The Wealth of Nations | C111: Adam Smith | D111: 1776 | E111: Business | F111: contemplative | G111: slow | H111: heavy | I111: economics, markets, labour | J111: 36 | K111: =ROUND(J111*$C$2,0)-0.1 -> 51.9 | L111: 3.9 | M111: 50000 | N111: Adam Smith's great inquiry into why some nations grow rich: the division of labour, beginning with a pin factory; the 'invisible hand' of self-interest; the case for free trade; and the dangers of monopolies and of merchants who conspire against the public. The founding text of economics — more humane, and more suspicious of business, than its reputation suggests.
A112: 108 | B112: On the Origin of Species | C112: Charles Darwin | D112: 1859 | E112: Non-Fiction | F112: contemplative | G112: slow | H112: heavy | I112: evolution, nature, science | J112: 30 | K112: =ROUND(J112*$C$2,0)-0.1 -> 43.9 | L112: 4 | M112: 140000 | N112: After decades of observation, from the Galápagos to the pigeon lofts of England, Charles Darwin set out his theory that species are not fixed but evolve, shaped over immense spans of time by natural selection. Written for the general Victorian reader, it remains clear, careful and patient, and it changed the way human beings understand themselves.
A113: 109 | B113: The Diary of a Young Girl | C113: Anne Frank | D113: 1947 | E113: Biography | F113: melancholy, hopeful | G113: steady | H113: medium | I113: hope, war, adolescence | J113: 24 | K113: =ROUND(J113*$C$2,0)-0.1 -> 34.9 | L113: 4.18 | M113: 3800000 | N113: In June 1942 Anne Frank is given a diary for her thirteenth birthday. Weeks later her Jewish family goes into hiding from the Nazis in the secret annex behind her father's Amsterdam office. For two years she writes about quarrels, first love, her hopes of becoming a writer and the constant fear of discovery, with startling wit and honesty. One of the most important books to come out of the Second World War.
A114: 110 | B114: Night | C114: Elie Wiesel | D114: 1956 | E114: Biography | F114: melancholy, unsettling | G114: fast | H114: light | I114: survival, faith, memory | J114: 20 | K114: =ROUND(J114*$C$2,0)-0.1 -> 28.9 | L114: 4.35 | M114: 1300000 | N114: In 1944 fifteen-year-old Elie Wiesel and his family are deported from their town in Transylvania to Auschwitz, and later to Buchenwald. In little more than a hundred pages he describes the selections, the death marches, his struggle to keep his father alive and the death of his faith. A Nobel Peace laureate's testimony: spare and unforgettable.
A115: 111 | B115: Silent Spring | C115: Rachel Carson | D115: 1962 | E115: Non-Fiction | F115: contemplative, unsettling | G115: steady | H115: medium | I115: environment, science, responsibility | J115: 28 | K115: =ROUND(J115*$C$2,0)-0.1 -> 40.9 | L115: 4 | M115: 60000 | N115: The marine biologist Rachel Carson documented how DDT and other synthetic pesticides, sprayed indiscriminately across America, were poisoning birds, fish, soil and people, opening with the fable of a town where no birds sing. The chemical industry attacked her ferociously; the book led to restrictions on DDT and helped launch the modern environmental movement.
A116: 112 | B116: A Brief History of Time | C116: Stephen Hawking | D116: 1988 | E116: Non-Fiction | F116: contemplative | G116: steady | H116: medium | I116: cosmology, time, science | J116: 28 | K116: =ROUND(J116*$C$2,0)-0.1 -> 40.9 | L116: 4.2 | M116: 450000 | N116: Stephen Hawking sets out to explain, with a single equation, the biggest questions in physics: how the universe began, what black holes are, whether time can run backwards and how it might all end. Famously bought by millions and finished by fewer, it is in fact a clear and witty guide for the curious non-scientist.
A117: 113 | B117: Guns, Germs, and Steel | C117: Jared Diamond | D117: 1997 | E117: History | F117: contemplative | G117: slow | H117: heavy | I117: geography, civilisation, inequality | J117: 36 | K117: =ROUND(J117*$C$2,0)-0.1 -> 51.9 | L117: 4.06 | M117: 480000 | N117: Why did Eurasian societies conquer the Americas, Africa and Australia, and not the other way round? Jared Diamond's Pulitzer-winning answer has nothing to do with race and everything to do with geography — which crops and animals could be domesticated, which way the continents run, and which germs travelled with them. Sweeping, argumentative and contested, it changed how a generation thinks about world history.
A118: 114 | B118: The Selfish Gene | C118: Richard Dawkins | D118: 1976 | E118: Non-Fiction | F118: contemplative | G118: steady | H118: medium | I118: evolution, biology, behaviour | J118: 30 | K118: =ROUND(J118*$C$2,0)-0.1 -> 43.9 | L118: 4.15 | M118: 140000 | N118: Richard Dawkins argues that evolution is best understood from the gene's point of view, with bodies as 'survival machines' built by genes to copy themselves. From there he explains altruism, selfishness and family, and coins a new word — 'meme' — for ideas that replicate. Clear, provocative and still argued over.
A119: 115 | B119: How to Win Friends and Influence People | C119: Dale Carnegie | D119: 1936 | E119: Business | F119: hopeful | G119: fast | H119: light | I119: communication, influence, self-improvement | J119: 22 | K119: =ROUND(J119*$C$2,0)-0.1 -> 31.9 | L119: 4.21 | M119: 1000000 | N119: Dale Carnegie's plain-spoken guide to getting along with people: remember names, listen more than you talk, don't criticise, let the other person save face. Built from anecdotes about Lincoln, salesmen and ordinary folk, it is the grandfather of the self-help shelf and has sold tens of millions of copies. Dated in places, still uncannily useful.
A120: 116 | B120: The 7 Habits of Highly Effective People | C120: Stephen R. Covey | D120: 1989 | E120: Business | F120: hopeful, contemplative | G120: steady | H120: medium | I120: habits, leadership, character | J120: 29 | K120: =ROUND(J120*$C$2,0)-0.1 -> 41.9 | L120: 4.12 | M120: 600000 | N120: Stephen Covey's principle-based framework for personal and professional effectiveness: be proactive, begin with the end in mind, put first things first, think win-win, seek first to understand, synergise, and sharpen the saw. Less a bag of tips than an argument that character matters more than technique. A fixture of corporate training rooms for over thirty years.
A121: 117 | B121: Atomic Habits | C121: James Clear | D121: 2018 | E121: Business | F121: hopeful | G121: fast | H121: light | I121: habits, productivity, self-improvement | J121: 32 | K121: =ROUND(J121*$C$2,0)-0.1 -> 45.9 | L121: 4.36 | M121: 1200000 | N121: James Clear argues that tiny improvements — one percent at a time — compound into remarkable results, and that good habits come from systems, not willpower. He lays out four simple laws: make it obvious, attractive, easy and satisfying. Practical, readable and full of examples from sport, business and science; the defining habit book of its decade.
... A127: 123 | B127: The Intelligent Investor | C127: Benjamin Graham | D127: 1949 | E127: Business | F127: contemplative | G127: slow | H127: heavy | I127: investing, discipline, value | J127: 37 | K127: =ROUND(J127*$C$2,0)-0.1 -> 53.9 | L127: 4.26 | M127: 90000 | N127: Benjamin Graham, the father of value investing and Warren Buffett's teacher, explains how to invest without losing your shirt: insist on a margin of safety, treat a share as part of a real business, and let the manic 'Mr Market' work for you rather than against you. Buffett has called it by far the best book about investing ever written.

Sheet By genre
A1: Catalogue summary by genre
A3: Genre | B3: No. of titles | C3: Avg wholesale cost ($) | D3: Avg shop price ($) | E3: Avg reader rating
A4: Literary | B4: =COUNTIF(Books!$E$5:$E$127,A4) -> 45 | C4: =AVERAGEIF(Books!$E$5:$E$127,A4,Books!$J$5:$J$127) -> 26.755556 | D4: =AVERAGEIF(Books!$E$5:$E$127,A4,Books!$K$5:$K$127) -> 38.877778 | E4: =AVERAGEIF(Books!$E$5:$E$127,A4,Books!$L$5:$L$127) -> 3.968
A5: Crime | B5: =COUNTIF(Books!$E$5:$E$127,A5) -> 10 | C5: =AVERAGEIF(Books!$E$5:$E$127,A5,Books!$J$5:$J$127) -> 27 | D5: =AVERAGEIF(Books!$E$5:$E$127,A5,Books!$K$5:$K$127) -> 39.1 | E5: =AVERAGEIF(Books!$E$5:$E$127,A5,Books!$L$5:$L$127) -> 4.137
A6: Sci-Fi | B6: =COUNTIF(Books!$E$5:$E$127,A6) -> 9 | C6: =AVERAGEIF(Books!$E$5:$E$127,A6,Books!$J$5:$J$127) -> 27.333333 | D6: =AVERAGEIF(Books!$E$5:$E$127,A6,Books!$K$5:$K$127) -> 39.566667 | E6: =AVERAGEIF(Books!$E$5:$E$127,A6,Books!$L$5:$L$127) -> 4.1388889
A7: Business | B7: =COUNTIF(Books!$E$5:$E$127,A7) -> 8 | C7: =AVERAGEIF(Books!$E$5:$E$127,A7,Books!$J$5:$J$127) -> 29.5 | D7: =AVERAGEIF(Books!$E$5:$E$127,A7,Books!$K$5:$K$127) -> 42.65 | E7: =AVERAGEIF(Books!$E$5:$E$127,A7,Books!$L$5:$L$127) -> 4.165
A8: History | B8: =COUNTIF(Books!$E$5:$E$127,A8) -> 8 | C8: =AVERAGEIF(Books!$E$5:$E$127,A8,Books!$J$5:$J$127) -> 32.75 | D8: =AVERAGEIF(Books!$E$5:$E$127,A8,Books!$K$5:$K$127) -> 47.4 | E8: =AVERAGEIF(Books!$E$5:$E$127,A8,Books!$L$5:$L$127) -> 4.03625
A9: Non-Fiction | B9: =COUNTIF(Books!$E$5:$E$127,A9) -> 8 | C9: =AVERAGEIF(Books!$E$5:$E$127,A9,Books!$J$5:$J$127) -> 31.75 | D9: =AVERAGEIF(Books!$E$5:$E$127,A9,Books!$K$5:$K$127) -> 46.275 | E9: =AVERAGEIF(Books!$E$5:$E$127,A9,Books!$L$5:$L$127) -> 4.155
A10: Biography | B10: =COUNTIF(Books!$E$5:$E$127,A10) -> 6 | C10: =AVERAGEIF(Books!$E$5:$E$127,A10,Books!$J$5:$J$127) -> 27.833333 | D10: =AVERAGEIF(Books!$E$5:$E$127,A10,Books!$K$5:$K$127) -> 40.4 | E10: =AVERAGEIF(Books!$E$5:$E$127,A10,Books!$L$5:$L$127) -> 4.3183333
A11: Fantasy | B11: =COUNTIF(Books!$E$5:$E$127,A11) -> 6 | C11: =AVERAGEIF(Books!$E$5:$E$127,A11,Books!$J$5:$J$127) -> 31 | D11: =AVERAGEIF(Books!$E$5:$E$127,A11,Books!$K$5:$K$127) -> 44.9 | E11: =AVERAGEIF(Books!$E$5:$E$127,A11,Books!$L$5:$L$127) -> 4.3816667
A12: Horror | B12: =COUNTIF(Books!$E$5:$E$127,A12) -> 6 | C12: =AVERAGEIF(Books!$E$5:$E$127,A12,Books!$J$5:$J$127) -> 24.333333 | D12: =AVERAGEIF(Books!$E$5:$E$127,A12,Books!$K$5:$K$127) -> 35.066667 | E12: =AVERAGEIF(Books!$E$5:$E$127,A12,Books!$L$5:$L$127) -> 3.9983333
A13: Children | B13: =COUNTIF(Books!$E$5:$E$127,A13) -> 4 | C13: =AVERAGEIF(Books!$E$5:$E$127,A13,Books!$J$5:$J$127) -> 20.5 | D13: =AVERAGEIF(Books!$E$5:$E$127,A13,Books!$K$5:$K$127) -> 29.65 | E13: =AVERAGEIF(Books!$E$5:$E$127,A13,Books!$L$5:$L$127) -> 4.27
A14: Philosophy | B14: =COUNTIF(Books!$E$5:$E$127,A14) -> 4 | C14: =AVERAGEIF(Books!$E$5:$E$127,A14,Books!$J$5:$J$127) -> 21.75 | D14: =AVERAGEIF(Books!$E$5:$E$127,A14,Books!$K$5:$K$127) -> 31.4 | E14: =AVERAGEIF(Books!$E$5:$E$127,A14,Books!$L$5:$L$127) -> 4.1125
A15: Romance | B15: =COUNTIF(Books!$E$5:$E$127,A15) -> 4 | C15: =AVERAGEIF(Books!$E$5:$E$127,A15,Books!$J$5:$J$127) -> 24 | D15: =AVERAGEIF(Books!$E$5:$E$127,A15,Books!$K$5:$K$127) -> 34.65 | E15: =AVERAGEIF(Books!$E$5:$E$127,A15,Books!$L$5:$L$127) -> 4.085
... A17: YA | B17: =COUNTIF(Books!$E$5:$E$127,A17) -> 2 | C17: =AVERAGEIF(Books!$E$5:$E$127,A17,Books!$J$5:$J$127) -> 28.5 | D17: =AVERAGEIF(Books!$E$5:$E$127,A17,Books!$K$5:$K$127) -> 41.4 | E17: =AVERAGEIF(Books!$E$5:$E$127,A17,Books!$L$5:$L$127) -> 4.36
A18: Total | B18: =SUM(B4:B17) -> 123 | C18: =AVERAGE(Books!$J$5:$J$127) -> 27.471545 | D18: =AVERAGE(Books!$K$5:$K$127) -> 39.834959 | E18: =AVERAGE(Books!$L$5:$L$127) -> 4.0895122

Sheet Notes
A1: Notes on this workbook
A3: Source: the BOOKS catalogue and RATINGS table in index.html of the Book_Game repository (Corner Books prototype).
A4: Wholesale cost is the price the shop pays the distributor in-game; stock is bought two copies at a time.
A5: Shop price is the game's automatic price: round(cost × markup) − $0.10. Change the markup on the Books sheet (C2) to re-price.
A6: Reader ratings are approximate real-world aggregates (Goodreads/StoryGraph-style) frozen in the game — representative, not current.
A7: Moods, pace, weight and themes are the game's tags used to match customers to books.
A8: Year: ancient works carry an approximate date as text (e.g. 'c. 8th century BC').
A9: Total titles: 123.
